deepecon/__init__.py
deepecon/core/__init__.py
deepecon/core/base.py
deepecon/core/condition.py
deepecon/core/logging.py
deepecon/core/errors/__init__.py
deepecon/core/errors/base.py
deepecon/core/errors/exist.py
deepecon/core/errors/length.py
deepecon/core/errors/not_found.py
deepecon/core/results/__init__.py
deepecon/core/results/base.py
deepecon/core/results/stata.py
deepecon/estimators/__init__.py
deepecon/estimators/_out.py
deepecon/estimators/ols.py
deepecon/transforms/__init__.py
deepecon/transforms/drop.py
deepecon/transforms/winsor2.py
deepecon/transforms/basic/__init__.py
deepecon/transforms/basic/base.py
deepecon/transforms/corr/__init__.py
deepecon/transforms/corr/base.py
deepecon/transforms/corr/pearson.py
deepecon-0.1.1.dist-info/METADATA
deepecon-0.1.1.dist-info/WHEEL
deepecon-0.1.1.dist-info/entry_points.txt
deepecon-0.1.1.dist-info/licenses/LICENSE
deepecon-0.1.1.dist-info/RECORD
