Metadata-Version: 2.4
Name: deepecon
Version: 0.1.1
Summary: A econometrics algorithms package in Python
Author-email: SongTan <sepinetam@gmail.com>
License: MIT
License-File: LICENSE
Requires-Python: >=3.11
Requires-Dist: numpy>=2.0.2
Requires-Dist: openpyxl>=3.1.5
Requires-Dist: pandas>=2.2.3
Requires-Dist: scipy>=1.16.1
